kasheesh_tools/__init__.py
kasheesh_tools/tool_cmd_parser.py
kasheesh_tools/tool_file_rw.py
kasheesh_tools/tool_logger.py
kasheesh_tools/tool_stats.py
kasheesh_tools-0.1.8.dist-info/LICENSE
kasheesh_tools-0.1.8.dist-info/METADATA
kasheesh_tools-0.1.8.dist-info/WHEEL
kasheesh_tools-0.1.8.dist-info/top_level.txt
kasheesh_tools-0.1.8.dist-info/RECORD
