Metadata-Version: 2.1
Name: kasheesh_tools
Version: 0.1.8
Summary: Standard Tools
Author-email: Haibo Yu <haibo.yu@kasheesh.co>
Project-URL: Homepage, https://github.com/fscbco/pytool-telegram
Classifier: Programming Language :: Python :: 3
Classifier: License :: OSI Approved :: MIT License
Classifier: Operating System :: OS Independent
Requires-Python: >=3.11
License-File: LICENSE
